tortoise/__init__.py
tortoise/api.py
tortoise/api_fast.py
tortoise/do_tts.py
tortoise/eval.py
tortoise/get_conditioning_latents.py
tortoise/is_this_from_tortoise.py
tortoise/read.py
tortoise/read_fast.py
tortoise/socket_client.py
tortoise/socket_server.py
tortoise/tts_stream.py
tortoise/data/got.txt
tortoise/data/layman.txt
tortoise/data/mel_norms.pth
tortoise/data/riding_hood.txt
tortoise/data/seal_copypasta.txt
tortoise/data/tokenizer.json
tortoise/models/__init__.py
tortoise/models/arch_util.py
tortoise/models/autoregressive.py
tortoise/models/classifier.py
tortoise/models/clvp.py
tortoise/models/cvvp.py
tortoise/models/diffusion_decoder.py
tortoise/models/hifigan_decoder.py
tortoise/models/random_latent_generator.py
tortoise/models/stream_generator.py
tortoise/models/transformer.py
tortoise/models/vocoder.py
tortoise/models/xtransformers.py
tortoise/utils/__init__.py
tortoise/utils/audio.py
tortoise/utils/diffusion.py
tortoise/utils/stft.py
tortoise/utils/text.py
tortoise/utils/tokenizer.py
tortoise/utils/typical_sampling.py
tortoise/utils/wav2vec_alignment.py
tortoise/voices/angie/1.wav
tortoise/voices/angie/2.wav
tortoise/voices/angie/3.wav
tortoise/voices/applejack/1.wav
tortoise/voices/applejack/2.wav
tortoise/voices/applejack/3.wav
tortoise/voices/cond_latent_example/pat.pth
tortoise/voices/daniel/1.wav
tortoise/voices/daniel/2.wav
tortoise/voices/daniel/3.wav
tortoise/voices/daniel/4.wav
tortoise/voices/deniro/1.wav
tortoise/voices/deniro/2.wav
tortoise/voices/deniro/3.wav
tortoise/voices/deniro/4.wav
tortoise/voices/emma/1.wav
tortoise/voices/emma/2.wav
tortoise/voices/emma/3.wav
tortoise/voices/freeman/1.wav
tortoise/voices/freeman/2.wav
tortoise/voices/freeman/3.wav
tortoise/voices/geralt/1.wav
tortoise/voices/geralt/2.wav
tortoise/voices/geralt/3.wav
tortoise/voices/halle/1.wav
tortoise/voices/halle/2.wav
tortoise/voices/halle/3.wav
tortoise/voices/jlaw/1.wav
tortoise/voices/jlaw/2.wav
tortoise/voices/jlaw/3.wav
tortoise/voices/jlaw/4.wav
tts_webui_tortoise_tts-3.0.3.dist-info/licenses/LICENSE
tts_webui_tortoise_tts-3.0.3.dist-info/METADATA
tts_webui_tortoise_tts-3.0.3.dist-info/WHEEL
tts_webui_tortoise_tts-3.0.3.dist-info/top_level.txt
tts_webui_tortoise_tts-3.0.3.dist-info/RECORD
