Metadata-Version: 2.4
Name: tts_webui.tortoise-tts
Version: 3.0.3
Summary: A high quality multi-voice text-to-speech library
Home-page: https://github.com/neonbjb/tortoise-tts
Author: James Betker
Author-email: james@adamant.ai
Classifier: Programming Language :: Python :: 3
Classifier: License :: OSI Approved :: Apache Software License
Classifier: Operating System :: OS Independent
Requires-Python: >=3.6
License-File: LICENSE
Requires-Dist: tqdm
Requires-Dist: rotary_embedding_torch
Requires-Dist: inflect
Requires-Dist: progressbar
Requires-Dist: einops
Requires-Dist: unidecode
Requires-Dist: scipy
Requires-Dist: librosa
Requires-Dist: transformers>=4.43.0
Requires-Dist: tokenizers
Dynamic: author
Dynamic: author-email
Dynamic: classifier
Dynamic: description
Dynamic: description-content-type
Dynamic: home-page
Dynamic: license-file
Dynamic: requires-dist
Dynamic: requires-python
Dynamic: summary
